{
  "info": {
    "title": "Token editor bug fixes",
    "media": ""
  },
  "changes": [
    {
      "id": "",
      "content": "Fixed a typo in the token editor message for not having permissions to view the default token."
    },
    {
      "id": "",
      "content": "Fixed a case where the token editor would not update the default token fully."
    },
    {
      "id": "",
      "content": "Fixed the token editor assuming the player cannot view the default token when the character simply doesn't have a default token."
    }
  ]
}